pytodo/__init__.py
pytodo/argparser.py
pytodo/priority.py
pytodo/quotes.py
pytodo/script.py
pytodo_package-0.1.1.dist-info/LICENSE
pytodo_package-0.1.1.dist-info/METADATA
pytodo_package-0.1.1.dist-info/WHEEL
pytodo_package-0.1.1.dist-info/top_level.txt
pytodo_package-0.1.1.dist-info/RECORD
