Metadata-Version: 2.1
Name: pytodo-package
Version: 0.1.1
Summary: A minimal command line todo list built with Python and MongoDB
Home-page: https://github.com/thescriptninja/pytodo
Author: Parth Paradkar
Author-email: parthparadkar3@gmail.com
Maintainer: Shubhashish Dixit
Maintainer-email: thisisshub@gmail.com
License: UNKNOWN
Platform: UNKNOWN
Requires-Dist: pymongo (==3.8.0)
Requires-Dist: astroid (==1.6.6)
Requires-Dist: autopep8 (==1.4.4)
Requires-Dist: backports.functools-lru-cache (==1.6.1)
Requires-Dist: configparser (==4.0.2)
Requires-Dist: enum34 (==1.1.6)
Requires-Dist: futures (==3.3.0)
Requires-Dist: isort (==4.3.21)
Requires-Dist: lazy-object-proxy (==1.4.3)
Requires-Dist: mccabe (==0.6.1)
Requires-Dist: pycodestyle (==2.5.0)
Requires-Dist: pylint (==1.9.5)
Requires-Dist: singledispatch (==3.4.0.3)
Requires-Dist: six (==1.13.0)
Requires-Dist: wrapt (==1.11.2)
